{
   "Avatar" : {
      "addPosition" : [ 1, 801 ],
      "mainAvatarOffset" : [ -298.9556274414062, -100.5221862792969 ]
   },
   "Kinect" : {
      "beamerFOV" : 0,
      "beamerPosition" : [ 0, 0 ],
      "kinectPosition" : [ 0, 0 ],
      "kinectScaleFact" : 0
   },
   "LightPointApp" : {
      "cabindimension" : [ 513, 464 ],
      "cabindimensioninside" : [ 465, 420 ],
      "cabinposition" : [ 1231, 544 ],
      "cabinpositioninside" : [ 1278, 578 ],
      "homeposition" : [ 1733, 438 ],
      "insidePoisiton" : [ 1579, 896 ],
      "scaredposition" : [ 702, 208 ],
      "startposition" : [ 677, 713 ],
      "watchposition" : [ 1614, 650 ]
   },
   "LinieApp" : {
      "anchorExplodeStartPositionBottom" : [ 1301, 709 ],
      "anchorExplodeStartPositionTop" : [ 1210, 575 ],
      "anchorStartPositionBottom" : [ 1802, 548 ],
      "anchorStartPositionTop" : [ 20, 483 ],
      "finalCirclePosition" : [ 968, 513 ]
   },
   "emotions" : {
      "anchorposition" : [ 1254, 336 ],
      "anchorpositionBottom" : [ 1345, 822 ],
      "animeomaskposition" : [ 1323, 382 ],
      "animeomaskradius" : 150,
      "emitterTopPosition" : [ 1491, 371 ],
      "emitterposition" : [ 783, 560 ],
      "repulsionbottomposition" : [ 1499, 720 ],
      "repulsioncenterposition" : [ 378, 953 ],
      "repulsionposition" : [ 1555, 997 ],
      "repulsiontopposition" : [ 1302, 184 ],
      "startposition" : [ 1226, 598 ]
   },
   "humania" : {
      "startposition" : [ 513, 391 ]
   }
}

